{
	"LINEAK-LINEAS": {
		"LINEA-LINEA": [
			{
				"KODEA-CODIGO": "A0651",
				"DESKRIPZIOA-DESCRIPCION": "BILBAO - BALMASEDA",
				"OPERADOREAREN_IZENA-NOMBRE_OPERADOR": "Enkarterri",
				"TARIFAK-TARIFA": "T1",
				"LINEA_MOTA_EU-TIPO_LINEA_EU": "Busa",
				"LINEA_MOTA_CAS-TIPO_LINEA_CAS": "Bus"
			},
			{
				"KODEA-CODIGO": "A0652",
				"DESKRIPZIOA-DESCRIPCION": "LANESTOSA - BALMASEDA",
				"OPERADOREAREN_IZENA-NOMBRE_OPERADOR": "Enkarterri",
				"TARIFAK-TARIFA": "T4",
				"LINEA_MOTA_EU-TIPO_LINEA_EU": "Busa",
				"LINEA_MOTA_CAS-TIPO_LINEA_CAS": "Bus"
			},
			{
				"KODEA-CODIGO": "A0653",
				"DESKRIPZIOA-DESCRIPCION": "TRUCIOS TURTZIOZ - ARTZENTALES",
				"OPERADOREAREN_IZENA-NOMBRE_OPERADOR": "Enkarterri",
				"TARIFAK-TARIFA": "T1",
				"LINEA_MOTA_EU-TIPO_LINEA_EU": "Busa",
				"LINEA_MOTA_CAS-TIPO_LINEA_CAS": "Bus"
			},
			{
				"KODEA-CODIGO": "A0654",
				"DESKRIPZIOA-DESCRIPCION": "BALMASEDA - Gurutzeta/Cruces - UPV/EHU",
				"OPERADOREAREN_IZENA-NOMBRE_OPERADOR": "Enkarterri",
				"TARIFAK-TARIFA": "T1",
				"LINEA_MOTA_EU-TIPO_LINEA_EU": "Busa",
				"LINEA_MOTA_CAS-TIPO_LINEA_CAS": "Bus"
			},
			{
				"KODEA-CODIGO": "A2151",
				"DESKRIPZIOA-DESCRIPCION": "Areeta/Las Arenas - LARRABETZU",
				"OPERADOREAREN_IZENA-NOMBRE_OPERADOR": "Txorierri - Mungialdea",
				"TARIFAK-TARIFA": "T1",
				"LINEA_MOTA_EU-TIPO_LINEA_EU": "Busa",
				"LINEA_MOTA_CAS-TIPO_LINEA_CAS": "Bus"
			},
			{
				"KODEA-CODIGO": "A2153",
				"DESKRIPZIOA-DESCRIPCION": "BILBAO - Txorierri - LARRABETZU",
				"OPERADOREAREN_IZENA-NOMBRE_OPERADOR": "Txorierri - Mungialdea",
				"TARIFAK-TARIFA": "T1",
				"LINEA_MOTA_EU-TIPO_LINEA_EU": "Busa",
				"LINEA_MOTA_CAS-TIPO_LINEA_CAS": "Bus"
			},
			{
				"KODEA-CODIGO": "A2161",
				"DESKRIPZIOA-DESCRIPCION": "Bizkaia Zubia/Puente Bizkaia - UPV/EHU",
				"OPERADOREAREN_IZENA-NOMBRE_OPERADOR": "Txorierri - Mungialdea",
				"TARIFAK-TARIFA": "T1",
				"LINEA_MOTA_EU-TIPO_LINEA_EU": "Busa",
				"LINEA_MOTA_CAS-TIPO_LINEA_CAS": "Bus"
			},
			{
				"KODEA-CODIGO": "A2162",
				"DESKRIPZIOA-DESCRIPCION": "Andramari/Santa Maria Getxo - UPV/EHU (Algorta)",
				"OPERADOREAREN_IZENA-NOMBRE_OPERADOR": "Txorierri - Mungialdea",
				"TARIFAK-TARIFA": "T1",
				"LINEA_MOTA_EU-TIPO_LINEA_EU": "Busa",
				"LINEA_MOTA_CAS-TIPO_LINEA_CAS": "Bus"
			},
			{
				"KODEA-CODIGO": "A2163",
				"DESKRIPZIOA-DESCRIPCION": "ERANDIO - UPV/EHU",
				"OPERADOREAREN_IZENA-NOMBRE_OPERADOR": "Txorierri - Mungialdea",
				"TARIFAK-TARIFA": "T1",
				"LINEA_MOTA_EU-TIPO_LINEA_EU": "Busa",
				"LINEA_MOTA_CAS-TIPO_LINEA_CAS": "Bus"
			},
			{
				"KODEA-CODIGO": "A2164",
				"DESKRIPZIOA-DESCRIPCION": "Andramari/Santa Maria Getxo - UPV/EHU (Fadura)",
				"OPERADOREAREN_IZENA-NOMBRE_OPERADOR": "Txorierri - Mungialdea",
				"TARIFAK-TARIFA": "T1",
				"LINEA_MOTA_EU-TIPO_LINEA_EU": "Busa",
				"LINEA_MOTA_CAS-TIPO_LINEA_CAS": "Bus"
			},
			{
				"KODEA-CODIGO": "A2166",
				"DESKRIPZIOA-DESCRIPCION": "Uribe Kosta - UPV/EHU",
				"OPERADOREAREN_IZENA-NOMBRE_OPERADOR": "Txorierri - Mungialdea",
				"TARIFAK-TARIFA": "T1",
				"LINEA_MOTA_EU-TIPO_LINEA_EU": "Busa",
				"LINEA_MOTA_CAS-TIPO_LINEA_CAS": "Bus"
			},
			{
				"KODEA-CODIGO": "A2312",
				"DESKRIPZIOA-DESCRIPCION": "Zabalburu - UPV/EHU  (Juan de Garay)",
				"OPERADOREAREN_IZENA-NOMBRE_OPERADOR": "Ezkerraldea - Meatzaldea",
				"TARIFAK-TARIFA": "T1",
				"LINEA_MOTA_EU-TIPO_LINEA_EU": "Busa",
				"LINEA_MOTA_CAS-TIPO_LINEA_CAS": "Bus"
			},
			{
				"KODEA-CODIGO": "A2314",
				"DESKRIPZIOA-DESCRIPCION": "BILBAO - Erandiogoikoa - UPV/EHU",
				"OPERADOREAREN_IZENA-NOMBRE_OPERADOR": "Ezkerraldea - Meatzaldea",
				"TARIFAK-TARIFA": "T1",
				"LINEA_MOTA_EU-TIPO_LINEA_EU": "Busa",
				"LINEA_MOTA_CAS-TIPO_LINEA_CAS": "Bus"
			},
			{
				"KODEA-CODIGO": "A2315",
				"DESKRIPZIOA-DESCRIPCION": "SANTURTZI - PORTUGALETE - UPV/EHU",
				"OPERADOREAREN_IZENA-NOMBRE_OPERADOR": "Euskotren Carretera",
				"TARIFAK-TARIFA": "T1",
				"LINEA_MOTA_EU-TIPO_LINEA_EU": "Busa",
				"LINEA_MOTA_CAS-TIPO_LINEA_CAS": "Bus"
			},
			{
				"KODEA-CODIGO": "A2316",
				"DESKRIPZIOA-DESCRIPCION": "SESTAO - UPV/EHU",
				"OPERADOREAREN_IZENA-NOMBRE_OPERADOR": "Euskotren Carretera",
				"TARIFAK-TARIFA": "T1",
				"LINEA_MOTA_EU-TIPO_LINEA_EU": "Busa",
				"LINEA_MOTA_CAS-TIPO_LINEA_CAS": "Bus"
			},
			{
				"KODEA-CODIGO": "A2318",
				"DESKRIPZIOA-DESCRIPCION": "Termibus - UPV/EHU (Autopista)",
				"OPERADOREAREN_IZENA-NOMBRE_OPERADOR": "Ezkerraldea - Meatzaldea",
				"TARIFAK-TARIFA": "T1",
				"LINEA_MOTA_EU-TIPO_LINEA_EU": "Busa",
				"LINEA_MOTA_CAS-TIPO_LINEA_CAS": "Bus"
			},
			{
				"KODEA-CODIGO": "A2321",
				"DESKRIPZIOA-DESCRIPCION": "Santutxu - UPV/EHU (Autopista)",
				"OPERADOREAREN_IZENA-NOMBRE_OPERADOR": "Ezkerraldea - Meatzaldea",
				"TARIFAK-TARIFA": "T1",
				"LINEA_MOTA_EU-TIPO_LINEA_EU": "Busa",
				"LINEA_MOTA_CAS-TIPO_LINEA_CAS": "Bus"
			},
			{
				"KODEA-CODIGO": "A2322",
				"DESKRIPZIOA-DESCRIPCION": "BILBAO - ERANDIO - Astrabudua - UPV/EHU",
				"OPERADOREAREN_IZENA-NOMBRE_OPERADOR": "Txorierri - Mungialdea",
				"TARIFAK-TARIFA": "T1",
				"LINEA_MOTA_EU-TIPO_LINEA_EU": "Busa",
				"LINEA_MOTA_CAS-TIPO_LINEA_CAS": "Bus"
			},
			{
				"KODEA-CODIGO": "A2324",
				"DESKRIPZIOA-DESCRIPCION": "BILBAO - UPV/EHU (Enekuri)",
				"OPERADOREAREN_IZENA-NOMBRE_OPERADOR": "Ezkerraldea - Meatzaldea",
				"TARIFAK-TARIFA": "T1",
				"LINEA_MOTA_EU-TIPO_LINEA_EU": "Busa",
				"LINEA_MOTA_CAS-TIPO_LINEA_CAS": "Bus"
			},
			{
				"KODEA-CODIGO": "A2326",
				"DESKRIPZIOA-DESCRIPCION": "BARAKALDO - UPV/EHU",
				"OPERADOREAREN_IZENA-NOMBRE_OPERADOR": "Euskotren Carretera",
				"TARIFAK-TARIFA": "T1",
				"LINEA_MOTA_EU-TIPO_LINEA_EU": "Busa",
				"LINEA_MOTA_CAS-TIPO_LINEA_CAS": "Bus"
			},
			{
				"KODEA-CODIGO": "A2336",
				"DESKRIPZIOA-DESCRIPCION": "MUSKIZ - UPV/EHU",
				"OPERADOREAREN_IZENA-NOMBRE_OPERADOR": "Euskotren Carretera",
				"TARIFAK-TARIFA": "T1",
				"LINEA_MOTA_EU-TIPO_LINEA_EU": "Busa",
				"LINEA_MOTA_CAS-TIPO_LINEA_CAS": "Bus"
			},
			{
				"KODEA-CODIGO": "A2610",
				"DESKRIPZIOA-DESCRIPCION": "GALDAKAO - UPV/EHU",
				"OPERADOREAREN_IZENA-NOMBRE_OPERADOR": "Nerbioi - Arratia - Durangaldea",
				"TARIFAK-TARIFA": "T1",
				"LINEA_MOTA_EU-TIPO_LINEA_EU": "Busa",
				"LINEA_MOTA_CAS-TIPO_LINEA_CAS": "Bus"
			},
			{
				"KODEA-CODIGO": "A2611",
				"DESKRIPZIOA-DESCRIPCION": "UGAO MIRABALLES - BASAURI - ETXEBARRI - UPV/EHU",
				"OPERADOREAREN_IZENA-NOMBRE_OPERADOR": "Nerbioi - Arratia - Durangaldea",
				"TARIFAK-TARIFA": "T1",
				"LINEA_MOTA_EU-TIPO_LINEA_EU": "Busa",
				"LINEA_MOTA_CAS-TIPO_LINEA_CAS": "Bus"
			},
			{
				"KODEA-CODIGO": "A3115",
				"DESKRIPZIOA-DESCRIPCION": "BILBAO - SANTURTZI",
				"OPERADOREAREN_IZENA-NOMBRE_OPERADOR": "Ezkerraldea - Meatzaldea",
				"TARIFAK-TARIFA": "T1",
				"LINEA_MOTA_EU-TIPO_LINEA_EU": "Busa",
				"LINEA_MOTA_CAS-TIPO_LINEA_CAS": "Bus"
			},
			{
				"KODEA-CODIGO": "A3122",
				"DESKRIPZIOA-DESCRIPCION": "BILBAO - SESTAO - Errepelega/Repelega",
				"OPERADOREAREN_IZENA-NOMBRE_OPERADOR": "Ezkerraldea - Meatzaldea",
				"TARIFAK-TARIFA": "T1",
				"LINEA_MOTA_EU-TIPO_LINEA_EU": "Busa",
				"LINEA_MOTA_CAS-TIPO_LINEA_CAS": "Bus"
			},
			{
				"KODEA-CODIGO": "A3129",
				"DESKRIPZIOA-DESCRIPCION": "Lutxana - Gurutzeta/Cruces - SANTURTZI",
				"OPERADOREAREN_IZENA-NOMBRE_OPERADOR": "Ezkerraldea - Meatzaldea",
				"TARIFAK-TARIFA": "T1",
				"LINEA_MOTA_EU-TIPO_LINEA_EU": "Busa",
				"LINEA_MOTA_CAS-TIPO_LINEA_CAS": "Bus"
			},
			{
				"KODEA-CODIGO": "A3135",
				"DESKRIPZIOA-DESCRIPCION": "SESTAO - Cabieces",
				"OPERADOREAREN_IZENA-NOMBRE_OPERADOR": "Ezkerraldea - Meatzaldea",
				"TARIFAK-TARIFA": "T1",
				"LINEA_MOTA_EU-TIPO_LINEA_EU": "Busa",
				"LINEA_MOTA_CAS-TIPO_LINEA_CAS": "Bus"
			},
			{
				"KODEA-CODIGO": "A3136",
				"DESKRIPZIOA-DESCRIPCION": "BILBAO - BARAKALDO - SANTURTZI",
				"OPERADOREAREN_IZENA-NOMBRE_OPERADOR": "Ezkerraldea - Meatzaldea",
				"TARIFAK-TARIFA": "T1",
				"LINEA_MOTA_EU-TIPO_LINEA_EU": "Busa",
				"LINEA_MOTA_CAS-TIPO_LINEA_CAS": "Bus"
			},
			{
				"KODEA-CODIGO": "A3137",
				"DESKRIPZIOA-DESCRIPCION": "BILBAO - BARAKALDO",
				"OPERADOREAREN_IZENA-NOMBRE_OPERADOR": "Ezkerraldea - Meatzaldea",
				"TARIFAK-TARIFA": "T1",
				"LINEA_MOTA_EU-TIPO_LINEA_EU": "Busa",
				"LINEA_MOTA_CAS-TIPO_LINEA_CAS": "Bus"
			},
			{
				"KODEA-CODIGO": "A3141",
				"DESKRIPZIOA-DESCRIPCION": "Gurutzeta/Cruces - Bagatza - VALLE DE TRAPAGA TRAPAGARAN",
				"OPERADOREAREN_IZENA-NOMBRE_OPERADOR": "Ezkerraldea - Meatzaldea",
				"TARIFAK-TARIFA": "T1",
				"LINEA_MOTA_EU-TIPO_LINEA_EU": "Busa",
				"LINEA_MOTA_CAS-TIPO_LINEA_CAS": "Bus"
			},
			{
				"KODEA-CODIGO": "A3144",
				"DESKRIPZIOA-DESCRIPCION": "BILBAO - Gurutzeta/Cruces - BARAKALDO (Ugarte)",
				"OPERADOREAREN_IZENA-NOMBRE_OPERADOR": "Ezkerraldea - Meatzaldea",
				"TARIFAK-TARIFA": "T1",
				"LINEA_MOTA_EU-TIPO_LINEA_EU": "Busa",
				"LINEA_MOTA_CAS-TIPO_LINEA_CAS": "Bus"
			},
			{
				"KODEA-CODIGO": "A3151",
				"DESKRIPZIOA-DESCRIPCION": "BILBAO - SANTURTZI  - PORTUGALETE (Autopista)",
				"OPERADOREAREN_IZENA-NOMBRE_OPERADOR": "Ezkerraldea - Meatzaldea",
				"TARIFAK-TARIFA": "T1",
				"LINEA_MOTA_EU-TIPO_LINEA_EU": "Busa",
				"LINEA_MOTA_CAS-TIPO_LINEA_CAS": "Bus"
			},
			{
				"KODEA-CODIGO": "A3223",
				"DESKRIPZIOA-DESCRIPCION": "BILBAO - LARRABETZU (Artxandako Tunelak/Tuneles Artxanda)",
				"OPERADOREAREN_IZENA-NOMBRE_OPERADOR": "Txorierri - Mungialdea",
				"TARIFAK-TARIFA": "T1",
				"LINEA_MOTA_EU-TIPO_LINEA_EU": "Busa",
				"LINEA_MOTA_CAS-TIPO_LINEA_CAS": "Bus"
			},
			{
				"KODEA-CODIGO": "A3224",
				"DESKRIPZIOA-DESCRIPCION": "BILBAO - DERIO - Teknologia Parkea/Parque Tecnológico",
				"OPERADOREAREN_IZENA-NOMBRE_OPERADOR": "Txorierri - Mungialdea",
				"TARIFAK-TARIFA": "T1",
				"LINEA_MOTA_EU-TIPO_LINEA_EU": "Busa",
				"LINEA_MOTA_CAS-TIPO_LINEA_CAS": "Bus"
			},
			{
				"KODEA-CODIGO": "A3225",
				"DESKRIPZIOA-DESCRIPCION": "BILBAO - LAUKIZ - MUNGIA",
				"OPERADOREAREN_IZENA-NOMBRE_OPERADOR": "Txorierri - Mungialdea",
				"TARIFAK-TARIFA": "T1",
				"LINEA_MOTA_EU-TIPO_LINEA_EU": "Busa",
				"LINEA_MOTA_CAS-TIPO_LINEA_CAS": "Bus"
			},
			{
				"KODEA-CODIGO": "A3247",
				"DESKRIPZIOA-DESCRIPCION": "BILBAO - Aireportua/Aeropuerto",
				"OPERADOREAREN_IZENA-NOMBRE_OPERADOR": "Txorierri - Mungialdea",
				"TARIFAK-TARIFA": "T3",
				"LINEA_MOTA_EU-TIPO_LINEA_EU": "Busa",
				"LINEA_MOTA_CAS-TIPO_LINEA_CAS": "Bus"
			},
			{
				"KODEA-CODIGO": "A3250",
				"DESKRIPZIOA-DESCRIPCION": "BILBAO - Teknologia Parkea/Parque Tecnológico (Artxandako Tunelak/Tuneles Artxanda)",
				"OPERADOREAREN_IZENA-NOMBRE_OPERADOR": "Txorierri - Mungialdea",
				"TARIFAK-TARIFA": "T1",
				"LINEA_MOTA_EU-TIPO_LINEA_EU": "Busa",
				"LINEA_MOTA_CAS-TIPO_LINEA_CAS": "Bus"
			},
			{
				"KODEA-CODIGO": "A3321",
				"DESKRIPZIOA-DESCRIPCION": "PORTUGALETE - ZIERBENA - La Arena - MUSKIZ",
				"OPERADOREAREN_IZENA-NOMBRE_OPERADOR": "Ezkerraldea - Meatzaldea",
				"TARIFAK-TARIFA": "T1",
				"LINEA_MOTA_EU-TIPO_LINEA_EU": "Busa",
				"LINEA_MOTA_CAS-TIPO_LINEA_CAS": "Bus"
			},
			{
				"KODEA-CODIGO": "A3323",
				"DESKRIPZIOA-DESCRIPCION": "PORTUGALETE - GALDAMES",
				"OPERADOREAREN_IZENA-NOMBRE_OPERADOR": "Enkarterri",
				"TARIFAK-TARIFA": "T1",
				"LINEA_MOTA_EU-TIPO_LINEA_EU": "Busa",
				"LINEA_MOTA_CAS-TIPO_LINEA_CAS": "Bus"
			},
			{
				"KODEA-CODIGO": "A3331",
				"DESKRIPZIOA-DESCRIPCION": "SESTAO - VALLE DE TRAPAGA TRAPAGARAN",
				"OPERADOREAREN_IZENA-NOMBRE_OPERADOR": "Ezkerraldea - Meatzaldea",
				"TARIFAK-TARIFA": "T1",
				"LINEA_MOTA_EU-TIPO_LINEA_EU": "Busa",
				"LINEA_MOTA_CAS-TIPO_LINEA_CAS": "Bus"
			},
			{
				"KODEA-CODIGO": "A3332",
				"DESKRIPZIOA-DESCRIPCION": "VALLE DE TRAPAGA TRAPAGARAN - SANTURTZI",
				"OPERADOREAREN_IZENA-NOMBRE_OPERADOR": "Ezkerraldea - Meatzaldea",
				"TARIFAK-TARIFA": "T1",
				"LINEA_MOTA_EU-TIPO_LINEA_EU": "Busa",
				"LINEA_MOTA_CAS-TIPO_LINEA_CAS": "Bus"
			},
			{
				"KODEA-CODIGO": "A3333",
				"DESKRIPZIOA-DESCRIPCION": "Gallarta - SANTURTZI",
				"OPERADOREAREN_IZENA-NOMBRE_OPERADOR": "Ezkerraldea - Meatzaldea",
				"TARIFAK-TARIFA": "T1",
				"LINEA_MOTA_EU-TIPO_LINEA_EU": "Busa",
				"LINEA_MOTA_CAS-TIPO_LINEA_CAS": "Bus"
			},
			{
				"KODEA-CODIGO": "A3334",
				"DESKRIPZIOA-DESCRIPCION": "SANTURTZI - BALMASEDA",
				"OPERADOREAREN_IZENA-NOMBRE_OPERADOR": "Enkarterri",
				"TARIFAK-TARIFA": "T1",
				"LINEA_MOTA_EU-TIPO_LINEA_EU": "Busa",
				"LINEA_MOTA_CAS-TIPO_LINEA_CAS": "Bus"
			},
			{
				"KODEA-CODIGO": "A3335",
				"DESKRIPZIOA-DESCRIPCION": "MUSKIZ - ZIERBENA - SESTAO",
				"OPERADOREAREN_IZENA-NOMBRE_OPERADOR": "Ezkerraldea - Meatzaldea",
				"TARIFAK-TARIFA": "T1",
				"LINEA_MOTA_EU-TIPO_LINEA_EU": "Busa",
				"LINEA_MOTA_CAS-TIPO_LINEA_CAS": "Bus"
			},
			{
				"KODEA-CODIGO": "A3336",
				"DESKRIPZIOA-DESCRIPCION": "BILBAO - MUSKIZ",
				"OPERADOREAREN_IZENA-NOMBRE_OPERADOR": "Ezkerraldea - Meatzaldea",
				"TARIFAK-TARIFA": "T1",
				"LINEA_MOTA_EU-TIPO_LINEA_EU": "Busa",
				"LINEA_MOTA_CAS-TIPO_LINEA_CAS": "Bus"
			},
			{
				"KODEA-CODIGO": "A3338",
				"DESKRIPZIOA-DESCRIPCION": "MUSKIZ - BARAKALDO - Areeta/Las Arenas",
				"OPERADOREAREN_IZENA-NOMBRE_OPERADOR": "Ezkerraldea - Meatzaldea",
				"TARIFAK-TARIFA": "T1",
				"LINEA_MOTA_EU-TIPO_LINEA_EU": "Busa",
				"LINEA_MOTA_CAS-TIPO_LINEA_CAS": "Bus"
			},
			{
				"KODEA-CODIGO": "A3339",
				"DESKRIPZIOA-DESCRIPCION": "Gurutzeta/Cruces-BARAKALDO-La Arena",
				"OPERADOREAREN_IZENA-NOMBRE_OPERADOR": "Ezkerraldea - Meatzaldea",
				"TARIFAK-TARIFA": "T1",
				"LINEA_MOTA_EU-TIPO_LINEA_EU": "Busa",
				"LINEA_MOTA_CAS-TIPO_LINEA_CAS": "Bus"
			},
			{
				"KODEA-CODIGO": "A3340",
				"DESKRIPZIOA-DESCRIPCION": "BILBAO - ABANTO Y CIERVANA ABANTO ZIERBENA - MUSKIZ (Autopista)",
				"OPERADOREAREN_IZENA-NOMBRE_OPERADOR": "Ezkerraldea - Meatzaldea",
				"TARIFAK-TARIFA": "T1",
				"LINEA_MOTA_EU-TIPO_LINEA_EU": "Busa",
				"LINEA_MOTA_CAS-TIPO_LINEA_CAS": "Bus"
			},
			{
				"KODEA-CODIGO": "A3341",
				"DESKRIPZIOA-DESCRIPCION": "BILBAO - Sodupe - Arespalditza Respaldiza",
				"OPERADOREAREN_IZENA-NOMBRE_OPERADOR": "Enkarterri",
				"TARIFAK-TARIFA": "T1",
				"LINEA_MOTA_EU-TIPO_LINEA_EU": "Busa",
				"LINEA_MOTA_CAS-TIPO_LINEA_CAS": "Bus"
			},
			{
				"KODEA-CODIGO": "A3342",
				"DESKRIPZIOA-DESCRIPCION": "BILBAO - Sodupe - ARTZINIEGA",
				"OPERADOREAREN_IZENA-NOMBRE_OPERADOR": "Enkarterri",
				"TARIFAK-TARIFA": "T1",
				"LINEA_MOTA_EU-TIPO_LINEA_EU": "Busa",
				"LINEA_MOTA_CAS-TIPO_LINEA_CAS": "Bus"
			},
			{
				"KODEA-CODIGO": "A3343",
				"DESKRIPZIOA-DESCRIPCION": "BILBAO - Sodupe - GORDEXOLA",
				"OPERADOREAREN_IZENA-NOMBRE_OPERADOR": "Enkarterri",
				"TARIFAK-TARIFA": "T1",
				"LINEA_MOTA_EU-TIPO_LINEA_EU": "Busa",
				"LINEA_MOTA_CAS-TIPO_LINEA_CAS": "Bus"
			},
			{
				"KODEA-CODIGO": "A3411",
				"DESKRIPZIOA-DESCRIPCION": "BILBAO - GETXO - Azkorri",
				"OPERADOREAREN_IZENA-NOMBRE_OPERADOR": "Euskotren Carretera",
				"TARIFAK-TARIFA": "T1",
				"LINEA_MOTA_EU-TIPO_LINEA_EU": "Busa",
				"LINEA_MOTA_CAS-TIPO_LINEA_CAS": "Bus"
			},
			{
				"KODEA-CODIGO": "A3414",
				"DESKRIPZIOA-DESCRIPCION": "BILBAO - GETXO (Artxandako tuneletatik/por túneles de Artxanda)",
				"OPERADOREAREN_IZENA-NOMBRE_OPERADOR": "Euskotren Carretera",
				"TARIFAK-TARIFA": "T1",
				"LINEA_MOTA_EU-TIPO_LINEA_EU": "Busa",
				"LINEA_MOTA_CAS-TIPO_LINEA_CAS": "Bus"
			},
			{
				"KODEA-CODIGO": "A3422",
				"DESKRIPZIOA-DESCRIPCION": "Areeta/Las Arenas - BERANGO",
				"OPERADOREAREN_IZENA-NOMBRE_OPERADOR": "Euskotren Carretera",
				"TARIFAK-TARIFA": "T1",
				"LINEA_MOTA_EU-TIPO_LINEA_EU": "Busa",
				"LINEA_MOTA_CAS-TIPO_LINEA_CAS": "Bus"
			},
			{
				"KODEA-CODIGO": "A3451",
				"DESKRIPZIOA-DESCRIPCION": "Areeta/Las Arenas  - Armintza",
				"OPERADOREAREN_IZENA-NOMBRE_OPERADOR": "Euskotren Carretera",
				"TARIFAK-TARIFA": "T1",
				"LINEA_MOTA_EU-TIPO_LINEA_EU": "Busa",
				"LINEA_MOTA_CAS-TIPO_LINEA_CAS": "Bus"
			},
			{
				"KODEA-CODIGO": "A3471",
				"DESKRIPZIOA-DESCRIPCION": "GETXO - Gurutzeta / Cruces (Faduratik / Por Fadura)",
				"OPERADOREAREN_IZENA-NOMBRE_OPERADOR": "Euskotren Carretera",
				"TARIFAK-TARIFA": "T1",
				"LINEA_MOTA_EU-TIPO_LINEA_EU": "Busa",
				"LINEA_MOTA_CAS-TIPO_LINEA_CAS": "Bus"
			},
			{
				"KODEA-CODIGO": "A3472",
				"DESKRIPZIOA-DESCRIPCION": "GETXO - Gurutzeta / Cruces (Areetatik/desde Las Arenas)",
				"OPERADOREAREN_IZENA-NOMBRE_OPERADOR": "Euskotren Carretera",
				"TARIFAK-TARIFA": "T1",
				"LINEA_MOTA_EU-TIPO_LINEA_EU": "Busa",
				"LINEA_MOTA_CAS-TIPO_LINEA_CAS": "Bus"
			},
			{
				"KODEA-CODIGO": "A3499",
				"DESKRIPZIOA-DESCRIPCION": "PLENTZIA - GORLIZ",
				"OPERADOREAREN_IZENA-NOMBRE_OPERADOR": "Euskotren Carretera",
				"TARIFAK-TARIFA": "T1",
				"LINEA_MOTA_EU-TIPO_LINEA_EU": "Busa",
				"LINEA_MOTA_CAS-TIPO_LINEA_CAS": "Bus"
			},
			{
				"KODEA-CODIGO": "A3512",
				"DESKRIPZIOA-DESCRIPCION": "BILBAO - LEKEITIO (Autopista)",
				"OPERADOREAREN_IZENA-NOMBRE_OPERADOR": "Busturialdea - Lea Artibai",
				"TARIFAK-TARIFA": "T1",
				"LINEA_MOTA_EU-TIPO_LINEA_EU": "Busa",
				"LINEA_MOTA_CAS-TIPO_LINEA_CAS": "Bus"
			},
			{
				"KODEA-CODIGO": "A3513",
				"DESKRIPZIOA-DESCRIPCION": "BILBAO - Hospital Galdakao Ospitalea - GERNIKA LUMO - EA - LEKEITIO",
				"OPERADOREAREN_IZENA-NOMBRE_OPERADOR": "Busturialdea - Lea Artibai",
				"TARIFAK-TARIFA": "T1",
				"LINEA_MOTA_EU-TIPO_LINEA_EU": "Busa",
				"LINEA_MOTA_CAS-TIPO_LINEA_CAS": "Bus"
			},
			{
				"KODEA-CODIGO": "A3514",
				"DESKRIPZIOA-DESCRIPCION": "BILBAO - AMOREBIETA ETXANO - GERNIKA LUMO",
				"OPERADOREAREN_IZENA-NOMBRE_OPERADOR": "Busturialdea - Lea Artibai",
				"TARIFAK-TARIFA": "T1",
				"LINEA_MOTA_EU-TIPO_LINEA_EU": "Busa",
				"LINEA_MOTA_CAS-TIPO_LINEA_CAS": "Bus"
			},
			{
				"KODEA-CODIGO": "A3515",
				"DESKRIPZIOA-DESCRIPCION": "BILBAO - AMOREBIETA ETXANO - GERNIKA LUMO - BERMEO",
				"OPERADOREAREN_IZENA-NOMBRE_OPERADOR": "Busturialdea - Lea Artibai",
				"TARIFAK-TARIFA": "T1",
				"LINEA_MOTA_EU-TIPO_LINEA_EU": "Busa",
				"LINEA_MOTA_CAS-TIPO_LINEA_CAS": "Bus"
			},
			{
				"KODEA-CODIGO": "A3516",
				"DESKRIPZIOA-DESCRIPCION": "BILBAO - MUNGIA (Autopista)",
				"OPERADOREAREN_IZENA-NOMBRE_OPERADOR": "Txorierri - Mungialdea",
				"TARIFAK-TARIFA": "T1",
				"LINEA_MOTA_EU-TIPO_LINEA_EU": "Busa",
				"LINEA_MOTA_CAS-TIPO_LINEA_CAS": "Bus"
			},
			{
				"KODEA-CODIGO": "A3517",
				"DESKRIPZIOA-DESCRIPCION": "BILBAO - DERIO - MUNGIA",
				"OPERADOREAREN_IZENA-NOMBRE_OPERADOR": "Txorierri - Mungialdea",
				"TARIFAK-TARIFA": "T1",
				"LINEA_MOTA_EU-TIPO_LINEA_EU": "Busa",
				"LINEA_MOTA_CAS-TIPO_LINEA_CAS": "Bus"
			},
			{
				"KODEA-CODIGO": "A3518",
				"DESKRIPZIOA-DESCRIPCION": "BILBAO -MUNGIA - BAKIO (Autopista)",
				"OPERADOREAREN_IZENA-NOMBRE_OPERADOR": "Txorierri - Mungialdea",
				"TARIFAK-TARIFA": "T1",
				"LINEA_MOTA_EU-TIPO_LINEA_EU": "Busa",
				"LINEA_MOTA_CAS-TIPO_LINEA_CAS": "Bus"
			},
			{
				"KODEA-CODIGO": "A3522",
				"DESKRIPZIOA-DESCRIPCION": "MUNGIA - DERIO - Gurutzeta/Cruces",
				"OPERADOREAREN_IZENA-NOMBRE_OPERADOR": "Txorierri - Mungialdea",
				"TARIFAK-TARIFA": "T1",
				"LINEA_MOTA_EU-TIPO_LINEA_EU": "Busa",
				"LINEA_MOTA_CAS-TIPO_LINEA_CAS": "Bus"
			},
			{
				"KODEA-CODIGO": "A3523",
				"DESKRIPZIOA-DESCRIPCION": "BILBAO - Hospital Galdakao Ospitalea - GERNIKA LUMO - AULESTI - LEKEITIO",
				"OPERADOREAREN_IZENA-NOMBRE_OPERADOR": "Busturialdea - Lea Artibai",
				"TARIFAK-TARIFA": "T1",
				"LINEA_MOTA_EU-TIPO_LINEA_EU": "Busa",
				"LINEA_MOTA_CAS-TIPO_LINEA_CAS": "Bus"
			},
			{
				"KODEA-CODIGO": "A3524",
				"DESKRIPZIOA-DESCRIPCION": "BERMEO - BAKIO",
				"OPERADOREAREN_IZENA-NOMBRE_OPERADOR": "Txorierri - Mungialdea",
				"TARIFAK-TARIFA": "T1",
				"LINEA_MOTA_EU-TIPO_LINEA_EU": "Taxia",
				"LINEA_MOTA_CAS-TIPO_LINEA_CAS": "Taxi"
			},
			{
				"KODEA-CODIGO": "A3525",
				"DESKRIPZIOA-DESCRIPCION": "GERNIKA LUMO - AMOREBIETA ETXANO  - UPV/EHU",
				"OPERADOREAREN_IZENA-NOMBRE_OPERADOR": "Busturialdea - Lea Artibai",
				"TARIFAK-TARIFA": "T1",
				"LINEA_MOTA_EU-TIPO_LINEA_EU": "Busa",
				"LINEA_MOTA_CAS-TIPO_LINEA_CAS": "Bus"
			},
			{
				"KODEA-CODIGO": "A3526",
				"DESKRIPZIOA-DESCRIPCION": "MUNGIA - GERNIKA LUMO - IBARRANGELU",
				"OPERADOREAREN_IZENA-NOMBRE_OPERADOR": "Busturialdea - Lea Artibai",
				"TARIFAK-TARIFA": "T1",
				"LINEA_MOTA_EU-TIPO_LINEA_EU": "Busa",
				"LINEA_MOTA_CAS-TIPO_LINEA_CAS": "Bus"
			},
			{
				"KODEA-CODIGO": "A3527",
				"DESKRIPZIOA-DESCRIPCION": "BILBAO - MUNGIA - BERMEO (Autopista)",
				"OPERADOREAREN_IZENA-NOMBRE_OPERADOR": "Txorierri - Mungialdea",
				"TARIFAK-TARIFA": "T1",
				"LINEA_MOTA_EU-TIPO_LINEA_EU": "Busa",
				"LINEA_MOTA_CAS-TIPO_LINEA_CAS": "Bus"
			},
			{
				"KODEA-CODIGO": "A3528",
				"DESKRIPZIOA-DESCRIPCION": "BERMEO - MUNGIA - DERIO - UPV/EHU",
				"OPERADOREAREN_IZENA-NOMBRE_OPERADOR": "Txorierri - Mungialdea",
				"TARIFAK-TARIFA": "T1",
				"LINEA_MOTA_EU-TIPO_LINEA_EU": "Busa",
				"LINEA_MOTA_CAS-TIPO_LINEA_CAS": "Bus"
			},
			{
				"KODEA-CODIGO": "A3529",
				"DESKRIPZIOA-DESCRIPCION": "MUNGIA - GAMIZ FIKA",
				"OPERADOREAREN_IZENA-NOMBRE_OPERADOR": "Txorierri - Mungialdea",
				"TARIFAK-TARIFA": "T1",
				"LINEA_MOTA_EU-TIPO_LINEA_EU": "Busa",
				"LINEA_MOTA_CAS-TIPO_LINEA_CAS": "Bus"
			},
			{
				"KODEA-CODIGO": "A3530",
				"DESKRIPZIOA-DESCRIPCION": "MUNGIA - MEÑAKA - ARRIETA",
				"OPERADOREAREN_IZENA-NOMBRE_OPERADOR": "Txorierri - Mungialdea",
				"TARIFAK-TARIFA": "T1",
				"LINEA_MOTA_EU-TIPO_LINEA_EU": "Busa",
				"LINEA_MOTA_CAS-TIPO_LINEA_CAS": "Bus"
			},
			{
				"KODEA-CODIGO": "A3531",
				"DESKRIPZIOA-DESCRIPCION": "LEIOA - Hospital Urduliz Ospitalea - GATIKA - MUNGIA",
				"OPERADOREAREN_IZENA-NOMBRE_OPERADOR": "Txorierri - Mungialdea",
				"TARIFAK-TARIFA": "T1",
				"LINEA_MOTA_EU-TIPO_LINEA_EU": "Busa",
				"LINEA_MOTA_CAS-TIPO_LINEA_CAS": "Bus"
			},
			{
				"KODEA-CODIGO": "A3532",
				"DESKRIPZIOA-DESCRIPCION": "GERNIKA LUMO - EA",
				"OPERADOREAREN_IZENA-NOMBRE_OPERADOR": "Busturialdea - Lea Artibai",
				"TARIFAK-TARIFA": "T1",
				"LINEA_MOTA_EU-TIPO_LINEA_EU": "Microbusa",
				"LINEA_MOTA_CAS-TIPO_LINEA_CAS": "Microbus"
			},
			{
				"KODEA-CODIGO": "A3533",
				"DESKRIPZIOA-DESCRIPCION": "MORGA - GERNIKA LUMO - MENDATA",
				"OPERADOREAREN_IZENA-NOMBRE_OPERADOR": "Busturialdea - Lea Artibai",
				"TARIFAK-TARIFA": "T1",
				"LINEA_MOTA_EU-TIPO_LINEA_EU": "Microbusa",
				"LINEA_MOTA_CAS-TIPO_LINEA_CAS": "Microbus"
			},
			{
				"KODEA-CODIGO": "A3534",
				"DESKRIPZIOA-DESCRIPCION": "ERRIGOITI - GERNIKA LUMO - EREÑO",
				"OPERADOREAREN_IZENA-NOMBRE_OPERADOR": "Busturialdea - Lea Artibai",
				"TARIFAK-TARIFA": "T1",
				"LINEA_MOTA_EU-TIPO_LINEA_EU": "Microbusa",
				"LINEA_MOTA_CAS-TIPO_LINEA_CAS": "Microbus"
			},
			{
				"KODEA-CODIGO": "A3535",
				"DESKRIPZIOA-DESCRIPCION": "LEKEITIO - AMOROTO",
				"OPERADOREAREN_IZENA-NOMBRE_OPERADOR": "Busturialdea - Lea Artibai",
				"TARIFAK-TARIFA": "T1",
				"LINEA_MOTA_EU-TIPO_LINEA_EU": "Microbusa",
				"LINEA_MOTA_CAS-TIPO_LINEA_CAS": "Microbus"
			},
			{
				"KODEA-CODIGO": "A3536",
				"DESKRIPZIOA-DESCRIPCION": "LEKEITIO - MENDEXA",
				"OPERADOREAREN_IZENA-NOMBRE_OPERADOR": "Busturialdea - Lea Artibai",
				"TARIFAK-TARIFA": "T1",
				"LINEA_MOTA_EU-TIPO_LINEA_EU": "Microbusa",
				"LINEA_MOTA_CAS-TIPO_LINEA_CAS": "Microbus"
			},
			{
				"KODEA-CODIGO": "A3537",
				"DESKRIPZIOA-DESCRIPCION": "PLENTZIA - GORLIZ - MUNGIA",
				"OPERADOREAREN_IZENA-NOMBRE_OPERADOR": "Txorierri - Mungialdea",
				"TARIFAK-TARIFA": "T1",
				"LINEA_MOTA_EU-TIPO_LINEA_EU": "Busa",
				"LINEA_MOTA_CAS-TIPO_LINEA_CAS": "Bus"
			},
			{
				"KODEA-CODIGO": "A3538",
				"DESKRIPZIOA-DESCRIPCION": "LEKEITIO-Barainka",
				"OPERADOREAREN_IZENA-NOMBRE_OPERADOR": "Busturialdea - Lea Artibai",
				"TARIFAK-TARIFA": "T1",
				"LINEA_MOTA_EU-TIPO_LINEA_EU": "Microbusa",
				"LINEA_MOTA_CAS-TIPO_LINEA_CAS": "Microbus"
			},
			{
				"KODEA-CODIGO": "A3613",
				"DESKRIPZIOA-DESCRIPCION": "BILBAO - UGAO MIRABALLES - OROZKO",
				"OPERADOREAREN_IZENA-NOMBRE_OPERADOR": "Nerbioi - Arratia - Durangaldea",
				"TARIFAK-TARIFA": "T1",
				"LINEA_MOTA_EU-TIPO_LINEA_EU": "Busa",
				"LINEA_MOTA_CAS-TIPO_LINEA_CAS": "Bus"
			},
			{
				"KODEA-CODIGO": "A3622",
				"DESKRIPZIOA-DESCRIPCION": "BILBAO - BASAURI - Artunduaga - San Miguel -ZARATAMO",
				"OPERADOREAREN_IZENA-NOMBRE_OPERADOR": "Nerbioi - Arratia - Durangaldea",
				"TARIFAK-TARIFA": "T1",
				"LINEA_MOTA_EU-TIPO_LINEA_EU": "Busa",
				"LINEA_MOTA_CAS-TIPO_LINEA_CAS": "Bus"
			},
			{
				"KODEA-CODIGO": "A3631",
				"DESKRIPZIOA-DESCRIPCION": "BILBAO - GALDAKAO - LARRABETZU",
				"OPERADOREAREN_IZENA-NOMBRE_OPERADOR": "Nerbioi - Arratia - Durangaldea",
				"TARIFAK-TARIFA": "T1",
				"LINEA_MOTA_EU-TIPO_LINEA_EU": "Busa",
				"LINEA_MOTA_CAS-TIPO_LINEA_CAS": "Bus"
			},
			{
				"KODEA-CODIGO": "A3632",
				"DESKRIPZIOA-DESCRIPCION": "BILBAO - ETXEBARRI - BASAURI - San Miguel (Begoña)",
				"OPERADOREAREN_IZENA-NOMBRE_OPERADOR": "Nerbioi - Arratia - Durangaldea",
				"TARIFAK-TARIFA": "T1",
				"LINEA_MOTA_EU-TIPO_LINEA_EU": "Busa",
				"LINEA_MOTA_CAS-TIPO_LINEA_CAS": "Bus"
			},
			{
				"KODEA-CODIGO": "A3641",
				"DESKRIPZIOA-DESCRIPCION": "Nerbioi Garaia/Alto Nervion - ARRIGORRIAGA - Hospital Galdakao Ospitalea",
				"OPERADOREAREN_IZENA-NOMBRE_OPERADOR": "Nerbioi - Arratia - Durangaldea",
				"TARIFAK-TARIFA": "T1",
				"LINEA_MOTA_EU-TIPO_LINEA_EU": "Busa",
				"LINEA_MOTA_CAS-TIPO_LINEA_CAS": "Bus"
			},
			{
				"KODEA-CODIGO": "A3642",
				"DESKRIPZIOA-DESCRIPCION": "BASAURI - Hospital Galdakao Ospitalea (Bengoetxe)",
				"OPERADOREAREN_IZENA-NOMBRE_OPERADOR": "Nerbioi - Arratia - Durangaldea",
				"TARIFAK-TARIFA": "T1",
				"LINEA_MOTA_EU-TIPO_LINEA_EU": "Busa",
				"LINEA_MOTA_CAS-TIPO_LINEA_CAS": "Bus"
			},
			{
				"KODEA-CODIGO": "A3911",
				"DESKRIPZIOA-DESCRIPCION": "BILBAO - Hospital Galdakao Ospitalea - LEMOA - DURANGO - ELORRIO",
				"OPERADOREAREN_IZENA-NOMBRE_OPERADOR": "Nerbioi - Arratia - Durangaldea",
				"TARIFAK-TARIFA": "T1",
				"LINEA_MOTA_EU-TIPO_LINEA_EU": "Busa",
				"LINEA_MOTA_CAS-TIPO_LINEA_CAS": "Bus"
			},
			{
				"KODEA-CODIGO": "A3912",
				"DESKRIPZIOA-DESCRIPCION": "BILBAO - Hospital Galdakao Ospitalea - LEMOA - DURANGO - ERMUA - EIBAR",
				"OPERADOREAREN_IZENA-NOMBRE_OPERADOR": "Nerbioi - Arratia - Durangaldea",
				"TARIFAK-TARIFA": "T1",
				"LINEA_MOTA_EU-TIPO_LINEA_EU": "Busa",
				"LINEA_MOTA_CAS-TIPO_LINEA_CAS": "Bus"
			},
			{
				"KODEA-CODIGO": "A3913",
				"DESKRIPZIOA-DESCRIPCION": "Arrazola - DURANGO",
				"OPERADOREAREN_IZENA-NOMBRE_OPERADOR": "Nerbioi - Arratia - Durangaldea",
				"TARIFAK-TARIFA": "T1",
				"LINEA_MOTA_EU-TIPO_LINEA_EU": "Busa",
				"LINEA_MOTA_CAS-TIPO_LINEA_CAS": "Bus"
			},
			{
				"KODEA-CODIGO": "A3915",
				"DESKRIPZIOA-DESCRIPCION": "BILBAO - DURANGO - ONDARROA (Autopista)",
				"OPERADOREAREN_IZENA-NOMBRE_OPERADOR": "Busturialdea - Lea Artibai",
				"TARIFAK-TARIFA": "T1",
				"LINEA_MOTA_EU-TIPO_LINEA_EU": "Busa",
				"LINEA_MOTA_CAS-TIPO_LINEA_CAS": "Bus"
			},
			{
				"KODEA-CODIGO": "A3916",
				"DESKRIPZIOA-DESCRIPCION": "BILBAO - ERMUA - ONDARROA (Autopista)",
				"OPERADOREAREN_IZENA-NOMBRE_OPERADOR": "Busturialdea - Lea Artibai",
				"TARIFAK-TARIFA": "T1",
				"LINEA_MOTA_EU-TIPO_LINEA_EU": "Busa",
				"LINEA_MOTA_CAS-TIPO_LINEA_CAS": "Bus"
			},
			{
				"KODEA-CODIGO": "A3917",
				"DESKRIPZIOA-DESCRIPCION": "BILBAO - Hospital Galdakao Ospitalea - LEMOA - ZEANURI",
				"OPERADOREAREN_IZENA-NOMBRE_OPERADOR": "Nerbioi - Arratia - Durangaldea",
				"TARIFAK-TARIFA": "T1",
				"LINEA_MOTA_EU-TIPO_LINEA_EU": "Busa",
				"LINEA_MOTA_CAS-TIPO_LINEA_CAS": "Bus"
			},
			{
				"KODEA-CODIGO": "A3922",
				"DESKRIPZIOA-DESCRIPCION": "MUNITIBAR ARBATZEGI GERRIKAITZ - ZIORTZA BOLIBAR - MARKINA XEMEIN - ETXEBARRIA",
				"OPERADOREAREN_IZENA-NOMBRE_OPERADOR": "Busturialdea - Lea Artibai",
				"TARIFAK-TARIFA": "T1",
				"LINEA_MOTA_EU-TIPO_LINEA_EU": "Microbusa",
				"LINEA_MOTA_CAS-TIPO_LINEA_CAS": "Microbus"
			},
			{
				"KODEA-CODIGO": "A3923",
				"DESKRIPZIOA-DESCRIPCION": "BILBAO - DURANGO - ELORRIO (Autopista)",
				"OPERADOREAREN_IZENA-NOMBRE_OPERADOR": "Nerbioi - Arratia - Durangaldea",
				"TARIFAK-TARIFA": "T1",
				"LINEA_MOTA_EU-TIPO_LINEA_EU": "Busa",
				"LINEA_MOTA_CAS-TIPO_LINEA_CAS": "Bus"
			},
			{
				"KODEA-CODIGO": "A3924",
				"DESKRIPZIOA-DESCRIPCION": "ERMUA - DURANGO - UPV/EHU",
				"OPERADOREAREN_IZENA-NOMBRE_OPERADOR": "Nerbioi - Arratia - Durangaldea",
				"TARIFAK-TARIFA": "T1",
				"LINEA_MOTA_EU-TIPO_LINEA_EU": "Busa",
				"LINEA_MOTA_CAS-TIPO_LINEA_CAS": "Bus"
			},
			{
				"KODEA-CODIGO": "A3925",
				"DESKRIPZIOA-DESCRIPCION": "BILBAO - LEMOA - OTXANDIO - UBIDE",
				"OPERADOREAREN_IZENA-NOMBRE_OPERADOR": "Nerbioi - Arratia - Durangaldea",
				"TARIFAK-TARIFA": "T1",
				"LINEA_MOTA_EU-TIPO_LINEA_EU": "Busa",
				"LINEA_MOTA_CAS-TIPO_LINEA_CAS": "Bus"
			},
			{
				"KODEA-CODIGO": "A3926",
				"DESKRIPZIOA-DESCRIPCION": "BILBAO - ERMUA - EIBAR (Autopista)",
				"OPERADOREAREN_IZENA-NOMBRE_OPERADOR": "Nerbioi - Arratia - Durangaldea",
				"TARIFAK-TARIFA": "T1",
				"LINEA_MOTA_EU-TIPO_LINEA_EU": "Busa",
				"LINEA_MOTA_CAS-TIPO_LINEA_CAS": "Bus"
			},
			{
				"KODEA-CODIGO": "A3927",
				"DESKRIPZIOA-DESCRIPCION": "BILBAO - LEMOA - ZEANURI (Autopista)",
				"OPERADOREAREN_IZENA-NOMBRE_OPERADOR": "Nerbioi - Arratia - Durangaldea",
				"TARIFAK-TARIFA": "T1",
				"LINEA_MOTA_EU-TIPO_LINEA_EU": "Busa",
				"LINEA_MOTA_CAS-TIPO_LINEA_CAS": "Bus"
			},
			{
				"KODEA-CODIGO": "A3928",
				"DESKRIPZIOA-DESCRIPCION": "ARTEA - ZEBERIO - UGAO MIRABALLES",
				"OPERADOREAREN_IZENA-NOMBRE_OPERADOR": "Nerbioi - Arratia - Durangaldea",
				"TARIFAK-TARIFA": "T1",
				"LINEA_MOTA_EU-TIPO_LINEA_EU": "Busa",
				"LINEA_MOTA_CAS-TIPO_LINEA_CAS": "Bus"
			},
			{
				"KODEA-CODIGO": "A3930",
				"DESKRIPZIOA-DESCRIPCION": "BILBAO - GALDAKAO (Autopista)",
				"OPERADOREAREN_IZENA-NOMBRE_OPERADOR": "Nerbioi - Arratia - Durangaldea",
				"TARIFAK-TARIFA": "T1",
				"LINEA_MOTA_EU-TIPO_LINEA_EU": "Busa",
				"LINEA_MOTA_CAS-TIPO_LINEA_CAS": "Bus"
			},
			{
				"KODEA-CODIGO": "A3931",
				"DESKRIPZIOA-DESCRIPCION": "GARAI - DURANGO",
				"OPERADOREAREN_IZENA-NOMBRE_OPERADOR": "Nerbioi - Arratia - Durangaldea",
				"TARIFAK-TARIFA": "T2",
				"LINEA_MOTA_EU-TIPO_LINEA_EU": "Taxia",
				"LINEA_MOTA_CAS-TIPO_LINEA_CAS": "Taxi"
			},
			{
				"KODEA-CODIGO": "A3932",
				"DESKRIPZIOA-DESCRIPCION": "GALDAKAO - Metro Bolueta",
				"OPERADOREAREN_IZENA-NOMBRE_OPERADOR": "Nerbioi - Arratia - Durangaldea",
				"TARIFAK-TARIFA": "",
				"LINEA_MOTA_EU-TIPO_LINEA_EU": "Busa",
				"LINEA_MOTA_CAS-TIPO_LINEA_CAS": "Bus"
			},
			{
				"KODEA-CODIGO": "A3933",
				"DESKRIPZIOA-DESCRIPCION": "BILBAO - DURANGO (Autopista)",
				"OPERADOREAREN_IZENA-NOMBRE_OPERADOR": "Nerbioi - Arratia - Durangaldea",
				"TARIFAK-TARIFA": "T1",
				"LINEA_MOTA_EU-TIPO_LINEA_EU": "Busa",
				"LINEA_MOTA_CAS-TIPO_LINEA_CAS": "Bus"
			}
		]
	}
}